LICENSE.md
README.md
pyproject.toml
overlappogram/__init__.py
overlappogram/cli.py
overlappogram/error.py
overlappogram/inversion.py
overlappogram/io.py
overlappogram/response.py
overlappogram/spectral.py
overlappogram.egg-info/PKG-INFO
overlappogram.egg-info/SOURCES.txt
overlappogram.egg-info/dependency_links.txt
overlappogram.egg-info/entry_points.txt
overlappogram.egg-info/requires.txt
overlappogram.egg-info/top_level.txt
tests/test_cli.py
tests/test_inversion.py
tests/test_io.py
tests/test_response.py
tests/test_spectral.py