Metadata-Version: 2.1
Name: overlappogram
Version: 0.0.9
Summary: Overlappogram unfolding and analysis software
Author-email: "J. Marcus Hughes" <hughes.jmb@gmail.com>, Dyana Beabout <dyana.l.beabout@nasa.gov>
Maintainer-email: "J. Marcus Hughes" <hughes.jmb@gmail.com>
License: ## Public Domain
Project-URL: Homepage, https://github.com/ECCCO-mission/overlappogram
Project-URL: Documentation, https://eccco-mission.github.io/overlappogram/
Project-URL: Repository, https://github.com/eccco-mission/overlappogram.git
Project-URL: Bug Tracker, https://github.com/eccco-mission/overlappogram/issues
Project-URL: Changelog, https://github.com/eccco-mission/overlappogram/blob/main/CHANGELOG.md
Keywords: overlappogram,solar,physics,analysis
Classifier: Development Status :: 4 - Beta
Classifier: Programming Language :: Python
Requires-Python: >=3.9
License-File: LICENSE.md
Requires-Dist: numpy<2.0.0
Requires-Dist: astropy
Requires-Dist: scikit-learn
Requires-Dist: pandas
Requires-Dist: pillow
Requires-Dist: matplotlib
Requires-Dist: photutils
Requires-Dist: scipy
Requires-Dist: ndcube
Requires-Dist: toml
Requires-Dist: click
Requires-Dist: tqdm
Provides-Extra: test
Requires-Dist: pytest; extra == "test"
Requires-Dist: pytest-doctestplus; extra == "test"
Requires-Dist: pytest-cov; extra == "test"
Requires-Dist: ruff; extra == "test"
Requires-Dist: coverage; extra == "test"
Provides-Extra: docs
Requires-Dist: sphinx; extra == "docs"
Requires-Dist: sphinx-autoapi; extra == "docs"
Requires-Dist: sphinx-automodapi; extra == "docs"
Requires-Dist: pydata-sphinx-theme; extra == "docs"
